{
    "4": {
        "n_train": 1502,
        "n_features_in": 16484,
        "n_features": 14,
        "n_classes": 7,
        "scale": false,
        "normalize": false,
        "train_accuracy": 0.9600532623169108,
        "train_f1_micro": 0.9600532623169108,
        "train_f1_macro": 0.955083571304417,
        "train_f1_weighted": 0.9599337229852392,
        "train_ROC": 0.9981608380192039,
        "n_test": 1503,
        "test_accuracy": 0.9421157684630739,
        "test_f1_micro": 0.9421157684630739,
        "test_f1_macro": 0.9218539297386565,
        "test_f1_weighted": 0.9417673947236681,
        "test_ROC": 0.9946805968491802,
        "solution": [689, 708, 784, 1025, 1028, 1395, 1700, 2550, 2647, 2762, 3278, 3865, 4175, 4256]
    },
    "5": {
        "n_train": 1502,
        "n_features_in": 16484,
        "n_features": 16,
        "n_classes": 7,
        "scale": false,
        "normalize": false,
        "train_accuracy": 0.9620505992010653,
        "train_f1_micro": 0.9620505992010653,
        "train_f1_macro": 0.9578509270516058,
        "train_f1_weighted": 0.9620286944789173,
        "train_ROC": 0.9980528890488797,
        "n_test": 1503,
        "test_accuracy": 0.9434464404524284,
        "test_f1_micro": 0.9434464404524284,
        "test_f1_macro": 0.9228178138698466,
        "test_f1_weighted": 0.9432083653629713,
        "test_ROC": 0.9949681505067497,
        "solution": [689, 708, 784, 1025, 1028, 1395, 1700, 1894, 2550, 2647, 2762, 3117, 3278, 3865, 4175, 4256]
    },
    "6": {
        "n_train": 1502,
        "n_features_in": 16484,
        "n_features": 20,
        "n_classes": 7,
        "scale": false,
        "normalize": false,
        "train_accuracy": 0.9687083888149135,
        "train_f1_micro": 0.9687083888149135,
        "train_f1_macro": 0.963291673678062,
        "train_f1_weighted": 0.9686730821903455,
        "train_ROC": 0.9985325547580516,
        "n_test": 1503,
        "test_accuracy": 0.9454424484364604,
        "test_f1_micro": 0.9454424484364604,
        "test_f1_macro": 0.9260447855829995,
        "test_f1_weighted": 0.9452594290227976,
        "test_ROC": 0.9949662652239012,
        "solution": [689, 708, 784, 1025, 1028, 1317, 1395, 1700, 1815, 1894, 2550, 2647, 2762, 3117, 3278, 3865, 4175, 4256, 5818, 14590]
    },
    "7": {
        "n_train": 1502,
        "n_features_in": 16484,
        "n_features": 22,
        "n_classes": 7,
        "scale": false,
        "normalize": false,
        "train_accuracy": 0.9753661784287616,
        "train_f1_micro": 0.9753661784287616,
        "train_f1_macro": 0.9709256204812527,
        "train_f1_weighted": 0.9753414260382187,
        "train_ROC": 0.9985922633673775,
        "n_test": 1503,
        "test_accuracy": 0.9427811044577512,
        "test_f1_micro": 0.9427811044577512,
        "test_f1_macro": 0.9220600347704471,
        "test_f1_weighted": 0.9425493834215316,
        "test_ROC": 0.9949649519862447,
        "solution": [689, 708, 784, 1025, 1028, 1317, 1395, 1700, 1815, 1894, 2550, 2557, 2647, 2762, 3117, 3278, 3865, 4175, 4256, 5818, 13497, 14590]
    },
    "8": {
        "n_train": 1502,
        "n_features_in": 16484,
        "n_features": 27,
        "n_classes": 7,
        "scale": false,
        "normalize": false,
        "train_accuracy": 0.9820239680426098,
        "train_f1_micro": 0.9820239680426098,
        "train_f1_macro": 0.9786777257034321,
        "train_f1_weighted": 0.982002603418529,
        "train_ROC": 0.9996160869976737,
        "n_test": 1503,
        "test_accuracy": 0.9441117764471058,
        "test_f1_micro": 0.9441117764471059,
        "test_f1_macro": 0.9259818751019455,
        "test_f1_weighted": 0.9437929539717406,
        "test_ROC": 0.9953619157619806,
        "solution": [689, 708, 784, 1025, 1028, 1176, 1317, 1395, 1700, 1815, 1845, 1854, 1894, 2550, 2557, 2647, 2762, 3117, 3278, 3865, 4175, 4256, 4872, 5818, 12318, 13497, 14590]
    },
    "9": {
        "n_train": 1502,
        "n_features_in": 16484,
        "n_features": 31,
        "n_classes": 7,
        "scale": false,
        "normalize": false,
        "train_accuracy": 0.9840213049267643,
        "train_f1_micro": 0.9840213049267643,
        "train_f1_macro": 0.9802021676216015,
        "train_f1_weighted": 0.9840022297178149,
        "train_ROC": 0.9998212058359702,
        "n_test": 1503,
        "test_accuracy": 0.93812375249501,
        "test_f1_micro": 0.93812375249501,
        "test_f1_macro": 0.9157392009260504,
        "test_f1_weighted": 0.9377161129056555,
        "test_ROC": 0.9945091251888746,
        "solution": [689, 708, 784, 1025, 1028, 1176, 1317, 1333, 1395, 1700, 1815, 1845, 1854, 1894, 2550, 2557, 2647, 2762, 3012, 3117, 3258, 3278, 3865, 4175, 4256, 4872, 5436, 5818, 12318, 13497, 14590]
    },
    "10": {
        "n_train": 1502,
        "n_features_in": 16484,
        "n_features": 34,
        "n_classes": 7,
        "scale": false,
        "normalize": false,
        "train_accuracy": 0.988681757656458,
        "train_f1_micro": 0.988681757656458,
        "train_f1_macro": 0.9857467901012574,
        "train_f1_weighted": 0.9886627857768916,
        "train_ROC": 0.9998953746302526,
        "n_test": 1503,
        "test_accuracy": 0.9407850964737192,
        "test_f1_micro": 0.9407850964737192,
        "test_f1_macro": 0.9185694567483775,
        "test_f1_weighted": 0.9402413894782087,
        "test_ROC": 0.9941501864168482,
        "solution": [689, 708, 784, 910, 1025, 1028, 1039, 1176, 1317, 1333, 1395, 1700, 1815, 1845, 1854, 1894, 2550, 2557, 2647, 2762, 3012, 3117, 3258, 3278, 3865, 4175, 4256, 4872, 5436, 5818, 10533, 12318, 13497, 14590]
    },
    "11": {
        "n_train": 1502,
        "n_features_in": 16484,
        "n_features": 36,
        "n_classes": 7,
        "scale": false,
        "normalize": false,
        "train_accuracy": 0.9913448735019973,
        "train_f1_micro": 0.9913448735019973,
        "train_f1_macro": 0.9885097615593913,
        "train_f1_weighted": 0.9913372418755912,
        "train_ROC": 0.9999338631637237,
        "n_test": 1503,
        "test_accuracy": 0.9441117764471058,
        "test_f1_micro": 0.9441117764471059,
        "test_f1_macro": 0.9193527966754914,
        "test_f1_weighted": 0.9436935030721183,
        "test_ROC": 0.9943733735195958,
        "solution": [689, 708, 784, 910, 1025, 1028, 1039, 1176, 1317, 1333, 1395, 1700, 1815, 1845, 1854, 1894, 2462, 2550, 2557, 2647, 2762, 3012, 3117, 3258, 3278, 3865, 4175, 4256, 4872, 5436, 5818, 10533, 12318, 13186, 13497, 14590]
    },
    "12": {
        "n_train": 1502,
        "n_features_in": 16484,
        "n_features": 39,
        "n_classes": 7,
        "scale": false,
        "normalize": false,
        "train_accuracy": 0.9946737683089214,
        "train_f1_micro": 0.9946737683089214,
        "train_f1_macro": 0.9933833269524562,
        "train_f1_weighted": 0.9946743859952564,
        "train_ROC": 0.9999601646133333,
        "n_test": 1503,
        "test_accuracy": 0.9414504324683965,
        "test_f1_micro": 0.9414504324683965,
        "test_f1_macro": 0.9193555377762609,
        "test_f1_weighted": 0.9410399007538159,
        "test_ROC": 0.9945288830476569,
        "solution": [646, 689, 708, 784, 910, 1025, 1028, 1039, 1176, 1317, 1333, 1395, 1696, 1700, 1815, 1845, 1854, 1894, 2462, 2550, 2557, 2647, 2762, 3012, 3117, 3258, 3278, 3865, 4175, 4256, 4872, 5436, 5818, 9314, 10533, 12318, 13186, 13497, 14590]
    },
    "13": {
        "n_train": 1502,
        "n_features_in": 16484,
        "n_features": 43,
        "n_classes": 7,
        "scale": false,
        "normalize": false,
        "train_accuracy": 0.9966711051930759,
        "train_f1_micro": 0.9966711051930759,
        "train_f1_macro": 0.9958100715254349,
        "train_f1_weighted": 0.996674388036558,
        "train_ROC": 0.9999813437858592,
        "n_test": 1503,
        "test_accuracy": 0.9447771124417831,
        "test_f1_micro": 0.9447771124417831,
        "test_f1_macro": 0.9216717322658007,
        "test_f1_weighted": 0.9443353544243567,
        "test_ROC": 0.9944026557214436,
        "solution": [122, 646, 689, 708, 784, 910, 1025, 1028, 1039, 1057, 1176, 1317, 1333, 1395, 1696, 1700, 1815, 1845, 1854, 1894, 2462, 2550, 2557, 2647, 2762, 3012, 3117, 3258, 3278, 3865, 4175, 4256, 4872, 5436, 5818, 9314, 10394, 10533, 11596, 12318, 13186, 13497, 14590]
    },
    "14": {
        "n_train": 1502,
        "n_features_in": 16484,
        "n_features": 45,
        "n_classes": 7,
        "scale": false,
        "normalize": false,
        "train_accuracy": 0.9966711051930759,
        "train_f1_micro": 0.9966711051930759,
        "train_f1_macro": 0.9958100715254349,
        "train_f1_weighted": 0.996674388036558,
        "train_ROC": 0.999981614446449,
        "n_test": 1503,
        "test_accuracy": 0.9461077844311377,
        "test_f1_micro": 0.9461077844311377,
        "test_f1_macro": 0.9263327781128297,
        "test_f1_weighted": 0.9457996219444244,
        "test_ROC": 0.9945089390209263,
        "solution": [122, 646, 689, 708, 784, 910, 1025, 1028, 1039, 1057, 1176, 1317, 1333, 1395, 1696, 1700, 1815, 1845, 1854, 1894, 2462, 2550, 2557, 2647, 2762, 3012, 3117, 3258, 3278, 3865, 4175, 4256, 4872, 4975, 5436, 5818, 9314, 10394, 10533, 11596, 12318, 13076, 13186, 13497, 14590]
    },
    "15": {
        "n_train": 1502,
        "n_features_in": 16484,
        "n_features": 48,
        "n_classes": 7,
        "scale": false,
        "normalize": false,
        "train_accuracy": 0.9980026631158455,
        "train_f1_micro": 0.9980026631158455,
        "train_f1_macro": 0.9984466320105968,
        "train_f1_weighted": 0.9980041489079613,
        "train_ROC": 0.9999898502921328,
        "n_test": 1503,
        "test_accuracy": 0.9421157684630739,
        "test_f1_micro": 0.9421157684630739,
        "test_f1_macro": 0.9191044062782598,
        "test_f1_weighted": 0.9417195154076923,
        "test_ROC": 0.994536592073478,
        "solution": [122, 646, 689, 708, 784, 910, 1025, 1028, 1039, 1057, 1176, 1317, 1333, 1395, 1696, 1700, 1815, 1845, 1854, 1894, 2462, 2550, 2557, 2647, 2762, 2763, 3012, 3117, 3258, 3278, 3865, 4175, 4256, 4872, 4975, 5436, 5818, 6894, 9314, 10394, 10533, 11596, 12318, 12601, 13076, 13186, 13497, 14590]
    },
    "16": {
        "n_train": 1502,
        "n_features_in": 16484,
        "n_features": 53,
        "n_classes": 7,
        "scale": false,
        "normalize": false,
        "train_accuracy": 0.9993342210386151,
        "train_f1_micro": 0.9993342210386151,
        "train_f1_macro": 0.9994894997823878,
        "train_f1_weighted": 0.9993347000764997,
        "train_ROC": 0.9999966555614012,
        "n_test": 1503,
        "test_accuracy": 0.9481037924151696,
        "test_f1_micro": 0.9481037924151696,
        "test_f1_macro": 0.9290174193617521,
        "test_f1_weighted": 0.9479364080974011,
        "test_ROC": 0.9947303532233727,
        "solution": [122, 195, 646, 689, 708, 784, 906, 910, 1025, 1028, 1039, 1057, 1176, 1317, 1333, 1395, 1696, 1700, 1815, 1845, 1854, 1894, 2462, 2550, 2557, 2647, 2762, 2763, 2785, 3012, 3117, 3258, 3278, 3865, 4175, 4256, 4872, 4975, 5436, 5818, 6894, 8275, 9314, 10394, 10533, 11596, 12318, 12601, 13076, 13186, 13497, 14590, 16303]
    },
    "17": {
        "n_train": 1502,
        "n_features_in": 16484,
        "n_features": 57,
        "n_classes": 7,
        "scale": false,
        "normalize": false,
        "train_accuracy": 1.0,
        "train_f1_micro": 1.0,
        "train_f1_macro": 1.0,
        "train_f1_weighted": 1.0,
        "train_ROC": 1.0,
        "n_test": 1503,
        "test_accuracy": 0.9474384564204924,
        "test_f1_micro": 0.9474384564204924,
        "test_f1_macro": 0.9256421806292889,
        "test_f1_weighted": 0.9471045483233881,
        "test_ROC": 0.9951171491309287,
        "solution": [122, 195, 646, 689, 708, 784, 906, 910, 1025, 1028, 1039, 1057, 1176, 1317, 1333, 1395, 1573, 1696, 1700, 1815, 1845, 1854, 1894, 2462, 2550, 2557, 2647, 2762, 2763, 2785, 3012, 3117, 3258, 3278, 3865, 4175, 4256, 4872, 4975, 5436, 5818, 6894, 7179, 8275, 9314, 10394, 10533, 11596, 12318, 12601, 13076, 13186, 13497, 14346, 14430, 14590, 16303]
    },
    "18": {
        "n_train": 1502,
        "n_features_in": 16484,
        "n_features": 60,
        "n_classes": 7,
        "scale": false,
        "normalize": false,
        "train_accuracy": 1.0,
        "train_f1_micro": 1.0,
        "train_f1_macro": 1.0,
        "train_f1_weighted": 1.0,
        "train_ROC": 1.0,
        "n_test": 1503,
        "test_accuracy": 0.9467731204258151,
        "test_f1_micro": 0.9467731204258152,
        "test_f1_macro": 0.9256510478448944,
        "test_f1_weighted": 0.9463869057891748,
        "test_ROC": 0.9954656812868282,
        "solution": [122, 195, 646, 689, 708, 784, 906, 910, 1025, 1028, 1039, 1057, 1176, 1317, 1333, 1395, 1573, 1596, 1696, 1700, 1815, 1845, 1854, 1894, 2462, 2550, 2557, 2647, 2762, 2763, 2785, 3012, 3117, 3185, 3258, 3278, 3865, 4175, 4256, 4872, 4975, 5436, 5818, 6254, 6894, 7179, 8275, 9314, 10394, 10533, 11596, 12318, 12601, 13076, 13186, 13497, 14346, 14430, 14590, 16303]
    },
    "19": {
        "n_train": 1502,
        "n_features_in": 16484,
        "n_features": 64,
        "n_classes": 7,
        "scale": false,
        "normalize": false,
        "train_accuracy": 1.0,
        "train_f1_micro": 1.0,
        "train_f1_macro": 1.0,
        "train_f1_weighted": 1.0,
        "train_ROC": 1.0,
        "n_test": 1503,
        "test_accuracy": 0.9434464404524284,
        "test_f1_micro": 0.9434464404524284,
        "test_f1_macro": 0.9212921261057344,
        "test_f1_weighted": 0.9431616448166584,
        "test_ROC": 0.9950452705792153,
        "solution": [122, 195, 646, 689, 708, 784, 906, 910, 1025, 1028, 1039, 1057, 1176, 1317, 1333, 1395, 1573, 1596, 1696, 1700, 1815, 1845, 1854, 1894, 2462, 2550, 2557, 2647, 2762, 2763, 2785, 3012, 3117, 3185, 3258, 3278, 3865, 4175, 4256, 4872, 4975, 5436, 5818, 6254, 6387, 6894, 7179, 8275, 8435, 9221, 9314, 10394, 10533, 11596, 12318, 12518, 12601, 13076, 13186, 13497, 14346, 14430, 14590, 16303]
    },
    "20": {
        "n_train": 1502,
        "n_features_in": 16484,
        "n_features": 66,
        "n_classes": 7,
        "scale": false,
        "normalize": false,
        "train_accuracy": 1.0,
        "train_f1_micro": 1.0,
        "train_f1_macro": 1.0,
        "train_f1_weighted": 1.0,
        "train_ROC": 1.0,
        "n_test": 1503,
        "test_accuracy": 0.9434464404524284,
        "test_f1_micro": 0.9434464404524284,
        "test_f1_macro": 0.9193653159700593,
        "test_f1_weighted": 0.94318270667232,
        "test_ROC": 0.9950250636757811,
        "solution": [0, 122, 195, 646, 689, 708, 784, 906, 910, 1025, 1028, 1039, 1057, 1176, 1317, 1333, 1395, 1573, 1596, 1696, 1700, 1815, 1845, 1854, 1894, 2462, 2550, 2557, 2647, 2762, 2763, 2785, 3012, 3117, 3185, 3258, 3278, 3865, 4175, 4256, 4872, 4975, 5436, 5818, 6254, 6387, 6894, 7179, 8275, 8435, 9221, 9314, 10394, 10533, 11596, 12318, 12518, 12601, 13076, 13186, 13497, 14013, 14346, 14430, 14590, 16303]
    },
    "21": {
        "n_train": 1502,
        "n_features_in": 16484,
        "n_features": 69,
        "n_classes": 7,
        "scale": false,
        "normalize": false,
        "train_accuracy": 1.0,
        "train_f1_micro": 1.0,
        "train_f1_macro": 1.0,
        "train_f1_weighted": 1.0,
        "train_ROC": 1.0,
        "n_test": 1503,
        "test_accuracy": 0.9441117764471058,
        "test_f1_micro": 0.9441117764471059,
        "test_f1_macro": 0.9208267952614377,
        "test_f1_weighted": 0.943934779856729,
        "test_ROC": 0.9948723711668331,
        "solution": [0, 1, 2, 3, 122, 195, 646, 689, 708, 784, 906, 910, 1025, 1028, 1039, 1057, 1176, 1317, 1333, 1395, 1573, 1596, 1696, 1700, 1815, 1845, 1854, 1894, 2462, 2550, 2557, 2647, 2762, 2763, 2785, 3012, 3117, 3185, 3258, 3278, 3865, 4175, 4256, 4872, 4975, 5436, 5818, 6254, 6387, 6894, 7179, 8275, 8435, 9221, 9314, 10394, 10533, 11596, 12318, 12518, 12601, 13076, 13186, 13497, 14013, 14346, 14430, 14590, 16303]
    },
    "22": {
        "n_train": 1502,
        "n_features_in": 16484,
        "n_features": 74,
        "n_classes": 7,
        "scale": false,
        "normalize": false,
        "train_accuracy": 1.0,
        "train_f1_micro": 1.0,
        "train_f1_macro": 1.0,
        "train_f1_weighted": 1.0,
        "train_ROC": 1.0,
        "n_test": 1503,
        "test_accuracy": 0.9434464404524284,
        "test_f1_micro": 0.9434464404524284,
        "test_f1_macro": 0.9220705596105299,
        "test_f1_weighted": 0.943246873493196,
        "test_ROC": 0.9950756102394259,
        "solution": [0, 1, 2, 3, 4, 5, 6, 7, 8, 122, 195, 646, 689, 708, 784, 906, 910, 1025, 1028, 1039, 1057, 1176, 1317, 1333, 1395, 1573, 1596, 1696, 1700, 1815, 1845, 1854, 1894, 2462, 2550, 2557, 2647, 2762, 2763, 2785, 3012, 3117, 3185, 3258, 3278, 3865, 4175, 4256, 4872, 4975, 5436, 5818, 6254, 6387, 6894, 7179, 8275, 8435, 9221, 9314, 10394, 10533, 11596, 12318, 12518, 12601, 13076, 13186, 13497, 14013, 14346, 14430, 14590, 16303]
    },
    "23": {
        "n_train": 1502,
        "n_features_in": 16484,
        "n_features": 75,
        "n_classes": 7,
        "scale": false,
        "normalize": false,
        "train_accuracy": 1.0,
        "train_f1_micro": 1.0,
        "train_f1_macro": 1.0,
        "train_f1_weighted": 1.0,
        "train_ROC": 1.0,
        "n_test": 1503,
        "test_accuracy": 0.9434464404524284,
        "test_f1_micro": 0.9434464404524284,
        "test_f1_macro": 0.922483784172425,
        "test_f1_weighted": 0.9432303017351237,
        "test_ROC": 0.9951039511536441,
        "solution": [0, 1, 2, 3, 4, 5, 6, 7, 8, 9, 122, 195, 646, 689, 708, 784, 906, 910, 1025, 1028, 1039, 1057, 1176, 1317, 1333, 1395, 1573, 1596, 1696, 1700, 1815, 1845, 1854, 1894, 2462, 2550, 2557, 2647, 2762, 2763, 2785, 3012, 3117, 3185, 3258, 3278, 3865, 4175, 4256, 4872, 4975, 5436, 5818, 6254, 6387, 6894, 7179, 8275, 8435, 9221, 9314, 10394, 10533, 11596, 12318, 12518, 12601, 13076, 13186, 13497, 14013, 14346, 14430, 14590, 16303]
    },
    "24": {
        "n_train": 1502,
        "n_features_in": 16484,
        "n_features": 80,
        "n_classes": 7,
        "scale": false,
        "normalize": false,
        "train_accuracy": 1.0,
        "train_f1_micro": 1.0,
        "train_f1_macro": 1.0,
        "train_f1_weighted": 1.0,
        "train_ROC": 1.0,
        "n_test": 1503,
        "test_accuracy": 0.9387890884896873,
        "test_f1_micro": 0.9387890884896873,
        "test_f1_macro": 0.9155011162508704,
        "test_f1_weighted": 0.9385937161093189,
        "test_ROC": 0.9953768253497908,
        "solution": [0, 1, 2, 3, 4, 5, 6, 7, 8, 9, 10, 11, 12, 13, 14, 122, 195, 646, 689, 708, 784, 906, 910, 1025, 1028, 1039, 1057, 1176, 1317, 1333, 1395, 1573, 1596, 1696, 1700, 1815, 1845, 1854, 1894, 2462, 2550, 2557, 2647, 2762, 2763, 2785, 3012, 3117, 3185, 3258, 3278, 3865, 4175, 4256, 4872, 4975, 5436, 5818, 6254, 6387, 6894, 7179, 8275, 8435, 9221, 9314, 10394, 10533, 11596, 12318, 12518, 12601, 13076, 13186, 13497, 14013, 14346, 14430, 14590, 16303]
    },
    "25": {
        "n_train": 1502,
        "n_features_in": 16484,
        "n_features": 83,
        "n_classes": 7,
        "scale": false,
        "normalize": false,
        "train_accuracy": 1.0,
        "train_f1_micro": 1.0,
        "train_f1_macro": 1.0,
        "train_f1_weighted": 1.0,
        "train_ROC": 1.0,
        "n_test": 1503,
        "test_accuracy": 0.9421157684630739,
        "test_f1_micro": 0.9421157684630739,
        "test_f1_macro": 0.9209426127730876,
        "test_f1_weighted": 0.9420055155716192,
        "test_ROC": 0.9953292450209321,
        "solution": [0, 1, 2, 3, 4, 5, 6, 7, 8, 9, 10, 11, 12, 13, 14, 15, 16, 17, 122, 195, 646, 689, 708, 784, 906, 910, 1025, 1028, 1039, 1057, 1176, 1317, 1333, 1395, 1573, 1596, 1696, 1700, 1815, 1845, 1854, 1894, 2462, 2550, 2557, 2647, 2762, 2763, 2785, 3012, 3117, 3185, 3258, 3278, 3865, 4175, 4256, 4872, 4975, 5436, 5818, 6254, 6387, 6894, 7179, 8275, 8435, 9221, 9314, 10394, 10533, 11596, 12318, 12518, 12601, 13076, 13186, 13497, 14013, 14346, 14430, 14590, 16303]
    },
    "26": {
        "n_train": 1502,
        "n_features_in": 16484,
        "n_features": 87,
        "n_classes": 7,
        "scale": false,
        "normalize": false,
        "train_accuracy": 1.0,
        "train_f1_micro": 1.0,
        "train_f1_macro": 1.0,
        "train_f1_weighted": 1.0,
        "train_ROC": 1.0,
        "n_test": 1503,
        "test_accuracy": 0.9421157684630739,
        "test_f1_micro": 0.9421157684630739,
        "test_f1_macro": 0.9199724531704797,
        "test_f1_weighted": 0.941939969879544,
        "test_ROC": 0.9954536422357277,
        "solution": [0, 1, 2, 3, 4, 5, 6, 7, 8, 9, 10, 11, 12, 13, 14, 15, 16, 17, 18, 19, 20, 21, 122, 195, 646, 689, 708, 784, 906, 910, 1025, 1028, 1039, 1057, 1176, 1317, 1333, 1395, 1573, 1596, 1696, 1700, 1815, 1845, 1854, 1894, 2462, 2550, 2557, 2647, 2762, 2763, 2785, 3012, 3117, 3185, 3258, 3278, 3865, 4175, 4256, 4872, 4975, 5436, 5818, 6254, 6387, 6894, 7179, 8275, 8435, 9221, 9314, 10394, 10533, 11596, 12318, 12518, 12601, 13076, 13186, 13497, 14013, 14346, 14430, 14590, 16303]
    },
    "27": {
        "n_train": 1502,
        "n_features_in": 16484,
        "n_features": 88,
        "n_classes": 7,
        "scale": false,
        "normalize": false,
        "train_accuracy": 1.0,
        "train_f1_micro": 1.0,
        "train_f1_macro": 1.0,
        "train_f1_weighted": 1.0,
        "train_ROC": 1.0,
        "n_test": 1503,
        "test_accuracy": 0.9434464404524284,
        "test_f1_micro": 0.9434464404524284,
        "test_f1_macro": 0.9232141125797718,
        "test_f1_weighted": 0.9433219157452741,
        "test_ROC": 0.9954954393881753,
        "solution": [0, 1, 2, 3, 4, 5, 6, 7, 8, 9, 10, 11, 12, 13, 14, 15, 16, 17, 18, 19, 20, 21, 22, 122, 195, 646, 689, 708, 784, 906, 910, 1025, 1028, 1039, 1057, 1176, 1317, 1333, 1395, 1573, 1596, 1696, 1700, 1815, 1845, 1854, 1894, 2462, 2550, 2557, 2647, 2762, 2763, 2785, 3012, 3117, 3185, 3258, 3278, 3865, 4175, 4256, 4872, 4975, 5436, 5818, 6254, 6387, 6894, 7179, 8275, 8435, 9221, 9314, 10394, 10533, 11596, 12318, 12518, 12601, 13076, 13186, 13497, 14013, 14346, 14430, 14590, 16303]
    },
    "28": {
        "n_train": 1502,
        "n_features_in": 16484,
        "n_features": 93,
        "n_classes": 7,
        "scale": false,
        "normalize": false,
        "train_accuracy": 1.0,
        "train_f1_micro": 1.0,
        "train_f1_macro": 1.0,
        "train_f1_weighted": 1.0,
        "train_ROC": 1.0,
        "n_test": 1503,
        "test_accuracy": 0.9394544244843646,
        "test_f1_micro": 0.9394544244843644,
        "test_f1_macro": 0.9160198743504303,
        "test_f1_weighted": 0.9391899827230809,
        "test_ROC": 0.995919121245377,
        "solution": [0, 1, 2, 3, 4, 5, 6, 7, 8, 9, 10, 11, 12, 13, 14, 15, 16, 17, 18, 19, 20, 21, 22, 23, 24, 25, 26, 27, 122, 195, 646, 689, 708, 784, 906, 910, 1025, 1028, 1039, 1057, 1176, 1317, 1333, 1395, 1573, 1596, 1696, 1700, 1815, 1845, 1854, 1894, 2462, 2550, 2557, 2647, 2762, 2763, 2785, 3012, 3117, 3185, 3258, 3278, 3865, 4175, 4256, 4872, 4975, 5436, 5818, 6254, 6387, 6894, 7179, 8275, 8435, 9221, 9314, 10394, 10533, 11596, 12318, 12518, 12601, 13076, 13186, 13497, 14013, 14346, 14430, 14590, 16303]
    },
    "29": {
        "n_train": 1502,
        "n_features_in": 16484,
        "n_features": 97,
        "n_classes": 7,
        "scale": false,
        "normalize": false,
        "train_accuracy": 1.0,
        "train_f1_micro": 1.0,
        "train_f1_macro": 1.0,
        "train_f1_weighted": 1.0,
        "train_ROC": 1.0,
        "n_test": 1503,
        "test_accuracy": 0.9421157684630739,
        "test_f1_micro": 0.9421157684630739,
        "test_f1_macro": 0.9195473165514777,
        "test_f1_weighted": 0.9419310165428789,
        "test_ROC": 0.9958659791744537,
        "solution": [0, 1, 2, 3, 4, 5, 6, 7, 8, 9, 10, 11, 12, 13, 14, 15, 16, 17, 18, 19, 20, 21, 22, 23, 24, 25, 26, 27, 28, 29, 30, 31, 122, 195, 646, 689, 708, 784, 906, 910, 1025, 1028, 1039, 1057, 1176, 1317, 1333, 1395, 1573, 1596, 1696, 1700, 1815, 1845, 1854, 1894, 2462, 2550, 2557, 2647, 2762, 2763, 2785, 3012, 3117, 3185, 3258, 3278, 3865, 4175, 4256, 4872, 4975, 5436, 5818, 6254, 6387, 6894, 7179, 8275, 8435, 9221, 9314, 10394, 10533, 11596, 12318, 12518, 12601, 13076, 13186, 13497, 14013, 14346, 14430, 14590, 16303]
    },
    "30": {
        "n_train": 1502,
        "n_features_in": 16484,
        "n_features": 101,
        "n_classes": 7,
        "scale": false,
        "normalize": false,
        "train_accuracy": 1.0,
        "train_f1_micro": 1.0,
        "train_f1_macro": 1.0,
        "train_f1_weighted": 1.0,
        "train_ROC": 1.0,
        "n_test": 1503,
        "test_accuracy": 0.9441117764471058,
        "test_f1_micro": 0.9441117764471059,
        "test_f1_macro": 0.9201717732054294,
        "test_f1_weighted": 0.9439455862209458,
        "test_ROC": 0.9961566869775437,
        "solution": [0, 1, 2, 3, 4, 5, 6, 7, 8, 9, 10, 11, 12, 13, 14, 15, 16, 17, 18, 19, 20, 21, 22, 23, 24, 25, 26, 27, 28, 29, 30, 31, 32, 33, 34, 35, 122, 195, 646, 689, 708, 784, 906, 910, 1025, 1028, 1039, 1057, 1176, 1317, 1333, 1395, 1573, 1596, 1696, 1700, 1815, 1845, 1854, 1894, 2462, 2550, 2557, 2647, 2762, 2763, 2785, 3012, 3117, 3185, 3258, 3278, 3865, 4175, 4256, 4872, 4975, 5436, 5818, 6254, 6387, 6894, 7179, 8275, 8435, 9221, 9314, 10394, 10533, 11596, 12318, 12518, 12601, 13076, 13186, 13497, 14013, 14346, 14430, 14590, 16303]
    },
    "31": {
        "n_train": 1502,
        "n_features_in": 16484,
        "n_features": 103,
        "n_classes": 7,
        "scale": false,
        "normalize": false,
        "train_accuracy": 1.0,
        "train_f1_micro": 1.0,
        "train_f1_macro": 1.0,
        "train_f1_weighted": 1.0,
        "train_ROC": 1.0,
        "n_test": 1503,
        "test_accuracy": 0.9414504324683965,
        "test_f1_micro": 0.9414504324683965,
        "test_f1_macro": 0.9205547678433674,
        "test_f1_weighted": 0.9414132660983595,
        "test_ROC": 0.9961839527582351,
        "solution": [0, 1, 2, 3, 4, 5, 6, 7, 8, 9, 10, 11, 12, 13, 14, 15, 16, 17, 18, 19, 20, 21, 22, 23, 24, 25, 26, 27, 28, 29, 30, 31, 32, 33, 34, 35, 36, 37, 122, 195, 646, 689, 708, 784, 906, 910, 1025, 1028, 1039, 1057, 1176, 1317, 1333, 1395, 1573, 1596, 1696, 1700, 1815, 1845, 1854, 1894, 2462, 2550, 2557, 2647, 2762, 2763, 2785, 3012, 3117, 3185, 3258, 3278, 3865, 4175, 4256, 4872, 4975, 5436, 5818, 6254, 6387, 6894, 7179, 8275, 8435, 9221, 9314, 10394, 10533, 11596, 12318, 12518, 12601, 13076, 13186, 13497, 14013, 14346, 14430, 14590, 16303]
    },
    "32": {
        "n_train": 1502,
        "n_features_in": 16484,
        "n_features": 106,
        "n_classes": 7,
        "scale": false,
        "normalize": false,
        "train_accuracy": 1.0,
        "train_f1_micro": 1.0,
        "train_f1_macro": 1.0,
        "train_f1_weighted": 1.0,
        "train_ROC": 1.0,
        "n_test": 1503,
        "test_accuracy": 0.9447771124417831,
        "test_f1_micro": 0.9447771124417831,
        "test_f1_macro": 0.9237304397518383,
        "test_f1_weighted": 0.9446586726403736,
        "test_ROC": 0.9961547659877823,
        "solution": [0, 1, 2, 3, 4, 5, 6, 7, 8, 9, 10, 11, 12, 13, 14, 15, 16, 17, 18, 19, 20, 21, 22, 23, 24, 25, 26, 27, 28, 29, 30, 31, 32, 33, 34, 35, 36, 37, 38, 39, 40, 122, 195, 646, 689, 708, 784, 906, 910, 1025, 1028, 1039, 1057, 1176, 1317, 1333, 1395, 1573, 1596, 1696, 1700, 1815, 1845, 1854, 1894, 2462, 2550, 2557, 2647, 2762, 2763, 2785, 3012, 3117, 3185, 3258, 3278, 3865, 4175, 4256, 4872, 4975, 5436, 5818, 6254, 6387, 6894, 7179, 8275, 8435, 9221, 9314, 10394, 10533, 11596, 12318, 12518, 12601, 13076, 13186, 13497, 14013, 14346, 14430, 14590, 16303]
    },
    "33": {
        "n_train": 1502,
        "n_features_in": 16484,
        "n_features": 111,
        "n_classes": 7,
        "scale": false,
        "normalize": false,
        "train_accuracy": 1.0,
        "train_f1_micro": 1.0,
        "train_f1_macro": 1.0,
        "train_f1_weighted": 1.0,
        "train_ROC": 1.0,
        "n_test": 1503,
        "test_accuracy": 0.948769128409847,
        "test_f1_micro": 0.948769128409847,
        "test_f1_macro": 0.9267346482232561,
        "test_f1_weighted": 0.9486509684982338,
        "test_ROC": 0.9964553273025574,
        "solution": [0, 1, 2, 3, 4, 5, 6, 7, 8, 9, 10, 11, 12, 13, 14, 15, 16, 17, 18, 19, 20, 21, 22, 23, 24, 25, 26, 27, 28, 29, 30, 31, 32, 33, 34, 35, 36, 37, 38, 39, 40, 41, 42, 43, 44, 45, 122, 195, 646, 689, 708, 784, 906, 910, 1025, 1028, 1039, 1057, 1176, 1317, 1333, 1395, 1573, 1596, 1696, 1700, 1815, 1845, 1854, 1894, 2462, 2550, 2557, 2647, 2762, 2763, 2785, 3012, 3117, 3185, 3258, 3278, 3865, 4175, 4256, 4872, 4975, 5436, 5818, 6254, 6387, 6894, 7179, 8275, 8435, 9221, 9314, 10394, 10533, 11596, 12318, 12518, 12601, 13076, 13186, 13497, 14013, 14346, 14430, 14590, 16303]
    },
    "34": {
        "n_train": 1502,
        "n_features_in": 16484,
        "n_features": 117,
        "n_classes": 7,
        "scale": false,
        "normalize": false,
        "train_accuracy": 1.0,
        "train_f1_micro": 1.0,
        "train_f1_macro": 1.0,
        "train_f1_weighted": 1.0,
        "train_ROC": 1.0,
        "n_test": 1503,
        "test_accuracy": 0.948769128409847,
        "test_f1_micro": 0.948769128409847,
        "test_f1_macro": 0.9262139641888186,
        "test_f1_weighted": 0.9485991424090614,
        "test_ROC": 0.9962448466707833,
        "solution": [0, 1, 2, 3, 4, 5, 6, 7, 8, 9, 10, 11, 12, 13, 14, 15, 16, 17, 18, 19, 20, 21, 22, 23, 24, 25, 26, 27, 28, 29, 30, 31, 32, 33, 34, 35, 36, 37, 38, 39, 40, 41, 42, 43, 44, 45, 46, 47, 48, 49, 50, 51, 122, 195, 646, 689, 708, 784, 906, 910, 1025, 1028, 1039, 1057, 1176, 1317, 1333, 1395, 1573, 1596, 1696, 1700, 1815, 1845, 1854, 1894, 2462, 2550, 2557, 2647, 2762, 2763, 2785, 3012, 3117, 3185, 3258, 3278, 3865, 4175, 4256, 4872, 4975, 5436, 5818, 6254, 6387, 6894, 7179, 8275, 8435, 9221, 9314, 10394, 10533, 11596, 12318, 12518, 12601, 13076, 13186, 13497, 14013, 14346, 14430, 14590, 16303]
    },
    "35": {
        "n_train": 1502,
        "n_features_in": 16484,
        "n_features": 120,
        "n_classes": 7,
        "scale": false,
        "normalize": false,
        "train_accuracy": 1.0,
        "train_f1_micro": 1.0,
        "train_f1_macro": 1.0,
        "train_f1_weighted": 1.0,
        "train_ROC": 1.0,
        "n_test": 1503,
        "test_accuracy": 0.9474384564204924,
        "test_f1_micro": 0.9474384564204924,
        "test_f1_macro": 0.9237822386315905,
        "test_f1_weighted": 0.9472053115546063,
        "test_ROC": 0.9963213458467243,
        "solution": [0, 1, 2, 3, 4, 5, 6, 7, 8, 9, 10, 11, 12, 13, 14, 15, 16, 17, 18, 19, 20, 21, 22, 23, 24, 25, 26, 27, 28, 29, 30, 31, 32, 33, 34, 35, 36, 37, 38, 39, 40, 41, 42, 43, 44, 45, 46, 47, 48, 49, 50, 51, 52, 53, 54, 122, 195, 646, 689, 708, 784, 906, 910, 1025, 1028, 1039, 1057, 1176, 1317, 1333, 1395, 1573, 1596, 1696, 1700, 1815, 1845, 1854, 1894, 2462, 2550, 2557, 2647, 2762, 2763, 2785, 3012, 3117, 3185, 3258, 3278, 3865, 4175, 4256, 4872, 4975, 5436, 5818, 6254, 6387, 6894, 7179, 8275, 8435, 9221, 9314, 10394, 10533, 11596, 12318, 12518, 12601, 13076, 13186, 13497, 14013, 14346, 14430, 14590, 16303]
    },
    "36": {
        "n_train": 1502,
        "n_features_in": 16484,
        "n_features": 121,
        "n_classes": 7,
        "scale": false,
        "normalize": false,
        "train_accuracy": 1.0,
        "train_f1_micro": 1.0,
        "train_f1_macro": 1.0,
        "train_f1_weighted": 1.0,
        "train_ROC": 1.0,
        "n_test": 1503,
        "test_accuracy": 0.9474384564204924,
        "test_f1_micro": 0.9474384564204924,
        "test_f1_macro": 0.9239326547316008,
        "test_f1_weighted": 0.9472447835845088,
        "test_ROC": 0.9963544074275161,
        "solution": [0, 1, 2, 3, 4, 5, 6, 7, 8, 9, 10, 11, 12, 13, 14, 15, 16, 17, 18, 19, 20, 21, 22, 23, 24, 25, 26, 27, 28, 29, 30, 31, 32, 33, 34, 35, 36, 37, 38, 39, 40, 41, 42, 43, 44, 45, 46, 47, 48, 49, 50, 51, 52, 53, 54, 55, 122, 195, 646, 689, 708, 784, 906, 910, 1025, 1028, 1039, 1057, 1176, 1317, 1333, 1395, 1573, 1596, 1696, 1700, 1815, 1845, 1854, 1894, 2462, 2550, 2557, 2647, 2762, 2763, 2785, 3012, 3117, 3185, 3258, 3278, 3865, 4175, 4256, 4872, 4975, 5436, 5818, 6254, 6387, 6894, 7179, 8275, 8435, 9221, 9314, 10394, 10533, 11596, 12318, 12518, 12601, 13076, 13186, 13497, 14013, 14346, 14430, 14590, 16303]
    },
    "37": {
        "n_train": 1502,
        "n_features_in": 16484,
        "n_features": 128,
        "n_classes": 7,
        "scale": false,
        "normalize": false,
        "train_accuracy": 1.0,
        "train_f1_micro": 1.0,
        "train_f1_macro": 1.0,
        "train_f1_weighted": 1.0,
        "train_ROC": 1.0,
        "n_test": 1503,
        "test_accuracy": 0.9421157684630739,
        "test_f1_micro": 0.9421157684630739,
        "test_f1_macro": 0.9158575225780349,
        "test_f1_weighted": 0.9417295318745038,
        "test_ROC": 0.9961306802292189,
        "solution": [0, 1, 2, 3, 4, 5, 6, 7, 8, 9, 10, 11, 12, 13, 14, 15, 16, 17, 18, 19, 20, 21, 22, 23, 24, 25, 26, 27, 28, 29, 30, 31, 32, 33, 34, 35, 36, 37, 38, 39, 40, 41, 42, 43, 44, 45, 46, 47, 48, 49, 50, 51, 52, 53, 54, 55, 56, 57, 58, 59, 60, 61, 62, 122, 195, 646, 689, 708, 784, 906, 910, 1025, 1028, 1039, 1057, 1176, 1317, 1333, 1395, 1573, 1596, 1696, 1700, 1815, 1845, 1854, 1894, 2462, 2550, 2557, 2647, 2762, 2763, 2785, 3012, 3117, 3185, 3258, 3278, 3865, 4175, 4256, 4872, 4975, 5436, 5818, 6254, 6387, 6894, 7179, 8275, 8435, 9221, 9314, 10394, 10533, 11596, 12318, 12518, 12601, 13076, 13186, 13497, 14013, 14346, 14430, 14590, 16303]
    },
    "38": {
        "n_train": 1502,
        "n_features_in": 16484,
        "n_features": 132,
        "n_classes": 7,
        "scale": false,
        "normalize": false,
        "train_accuracy": 1.0,
        "train_f1_micro": 1.0,
        "train_f1_macro": 1.0,
        "train_f1_weighted": 1.0,
        "train_ROC": 1.0,
        "n_test": 1503,
        "test_accuracy": 0.9441117764471058,
        "test_f1_micro": 0.9441117764471059,
        "test_f1_macro": 0.919448073746669,
        "test_f1_weighted": 0.9437712284566114,
        "test_ROC": 0.9961090578785016,
        "solution": [0, 1, 2, 3, 4, 5, 6, 7, 8, 9, 10, 11, 12, 13, 14, 15, 16, 17, 18, 19, 20, 21, 22, 23, 24, 25, 26, 27, 28, 29, 30, 31, 32, 33, 34, 35, 36, 37, 38, 39, 40, 41, 42, 43, 44, 45, 46, 47, 48, 49, 50, 51, 52, 53, 54, 55, 56, 57, 58, 59, 60, 61, 62, 63, 64, 65, 66, 122, 195, 646, 689, 708, 784, 906, 910, 1025, 1028, 1039, 1057, 1176, 1317, 1333, 1395, 1573, 1596, 1696, 1700, 1815, 1845, 1854, 1894, 2462, 2550, 2557, 2647, 2762, 2763, 2785, 3012, 3117, 3185, 3258, 3278, 3865, 4175, 4256, 4872, 4975, 5436, 5818, 6254, 6387, 6894, 7179, 8275, 8435, 9221, 9314, 10394, 10533, 11596, 12318, 12518, 12601, 13076, 13186, 13497, 14013, 14346, 14430, 14590, 16303]
    },
    "39": {
        "n_train": 1502,
        "n_features_in": 16484,
        "n_features": 135,
        "n_classes": 7,
        "scale": false,
        "normalize": false,
        "train_accuracy": 1.0,
        "train_f1_micro": 1.0,
        "train_f1_macro": 1.0,
        "train_f1_weighted": 1.0,
        "train_ROC": 1.0,
        "n_test": 1503,
        "test_accuracy": 0.9441117764471058,
        "test_f1_micro": 0.9441117764471059,
        "test_f1_macro": 0.9190023929186103,
        "test_f1_weighted": 0.9436705816211548,
        "test_ROC": 0.9960863946473503,
        "solution": [0, 1, 2, 3, 4, 5, 6, 7, 8, 9, 10, 11, 12, 13, 14, 15, 16, 17, 18, 19, 20, 21, 22, 23, 24, 25, 26, 27, 28, 29, 30, 31, 32, 33, 34, 35, 36, 37, 38, 39, 40, 41, 42, 43, 44, 45, 46, 47, 48, 49, 50, 51, 52, 53, 54, 55, 56, 57, 58, 59, 60, 61, 62, 63, 64, 65, 66, 67, 68, 69, 122, 195, 646, 689, 708, 784, 906, 910, 1025, 1028, 1039, 1057, 1176, 1317, 1333, 1395, 1573, 1596, 1696, 1700, 1815, 1845, 1854, 1894, 2462, 2550, 2557, 2647, 2762, 2763, 2785, 3012, 3117, 3185, 3258, 3278, 3865, 4175, 4256, 4872, 4975, 5436, 5818, 6254, 6387, 6894, 7179, 8275, 8435, 9221, 9314, 10394, 10533, 11596, 12318, 12518, 12601, 13076, 13186, 13497, 14013, 14346, 14430, 14590, 16303]
    },
    "40": {
        "n_train": 1502,
        "n_features_in": 16484,
        "n_features": 139,
        "n_classes": 7,
        "scale": false,
        "normalize": false,
        "train_accuracy": 1.0,
        "train_f1_micro": 1.0,
        "train_f1_macro": 1.0,
        "train_f1_weighted": 1.0,
        "train_ROC": 1.0,
        "n_test": 1503,
        "test_accuracy": 0.9441117764471058,
        "test_f1_micro": 0.9441117764471059,
        "test_f1_macro": 0.9207803139783108,
        "test_f1_weighted": 0.9437954968754942,
        "test_ROC": 0.996167986888158,
        "solution": [0, 1, 2, 3, 4, 5, 6, 7, 8, 9, 10, 11, 12, 13, 14, 15, 16, 17, 18, 19, 20, 21, 22, 23, 24, 25, 26, 27, 28, 29, 30, 31, 32, 33, 34, 35, 36, 37, 38, 39, 40, 41, 42, 43, 44, 45, 46, 47, 48, 49, 50, 51, 52, 53, 54, 55, 56, 57, 58, 59, 60, 61, 62, 63, 64, 65, 66, 67, 68, 69, 70, 71, 72, 73, 122, 195, 646, 689, 708, 784, 906, 910, 1025, 1028, 1039, 1057, 1176, 1317, 1333, 1395, 1573, 1596, 1696, 1700, 1815, 1845, 1854, 1894, 2462, 2550, 2557, 2647, 2762, 2763, 2785, 3012, 3117, 3185, 3258, 3278, 3865, 4175, 4256, 4872, 4975, 5436, 5818, 6254, 6387, 6894, 7179, 8275, 8435, 9221, 9314, 10394, 10533, 11596, 12318, 12518, 12601, 13076, 13186, 13497, 14013, 14346, 14430, 14590, 16303]
    }
}