{
    "1": {
        "n_train": 48098,
        "n_features_in": 4443,
        "n_classes": 33,
        "filter_genes": false,
        "normalize": true,
        "log": true,
        "scale": true,
        "high_var": false,
        "ordered": true,
        "rho": 0.4,
        "alpha": 0.00022507314877335134,
        "rs": 1000,
        "min_coverage": 1.0082377344369888,
        "solution": [3411, 2534, 2639, 2205, 1786, 863, 3454, 1477, 656, 449, 1219, 1305, 110, 2057, 771],
        "n_features": 15
    },
    "2": {
        "n_train": 48098,
        "n_features_in": 4443,
        "n_classes": 33,
        "filter_genes": false,
        "normalize": true,
        "log": true,
        "scale": true,
        "high_var": false,
        "ordered": true,
        "rho": 0.4,
        "alpha": 0.00045014629754670267,
        "rs": 1000,
        "min_coverage": 2.009337857365608,
        "solution": [1665, 2491, 1597, 1413, 2362, 3901, 2806, 294, 4289, 2505, 247, 2535, 2827, 2204, 557, 748, 2492, 2789, 3454, 2534, 1470],
        "n_features": 21
    },
    "3": {
        "n_train": 48098,
        "n_features_in": 4443,
        "n_classes": 33,
        "filter_genes": false,
        "normalize": true,
        "log": true,
        "scale": true,
        "high_var": false,
        "ordered": true,
        "rho": 0.3333333333333333,
        "alpha": 0.0006752194463200541,
        "rs": 1000,
        "min_coverage": 3.0700729489326477,
        "solution": [2008, 1383, 2532, 2205, 2535, 2765, 1191, 1489, 1120, 611, 2491, 11, 2484, 2534, 2586, 94, 557, 137, 3985, 1418, 370, 551, 1841, 2166, 1000, 3738, 225, 656, 3213],
        "n_features": 29
    },
    "4": {
        "n_train": 48098,
        "n_features_in": 4443,
        "n_classes": 33,
        "filter_genes": false,
        "normalize": true,
        "log": true,
        "scale": true,
        "high_var": false,
        "ordered": true,
        "rho": 0.3333333333333333,
        "alpha": 0.0009002925950934053,
        "rs": 1000,
        "min_coverage": 4.087340995669365,
        "solution": [611, 2765, 3295, 1489, 2639, 1388, 1421, 2491, 4109, 745, 3877, 1546, 3411, 3311, 1835, 2912, 2181, 1224, 3061, 2914, 1471, 2534, 1966, 2665, 1762, 2480, 1054, 4242, 4176, 2774, 1417, 1243, 508, 3831],
        "n_features": 34
    },
    "5": {
        "n_train": 48098,
        "n_features_in": 4443,
        "n_classes": 33,
        "filter_genes": false,
        "normalize": true,
        "log": true,
        "scale": true,
        "high_var": false,
        "ordered": true,
        "rho": 0.3333333333333333,
        "alpha": 0.0011253657438667567,
        "rs": 1000,
        "min_coverage": 5.061756094917655,
        "solution": [115, 1388, 1679, 3411, 2532, 1054, 2243, 2534, 2491, 1597, 1712, 1880, 611, 1791, 318, 567, 234, 1489, 1467, 3454, 844, 497, 2055, 3227, 2665, 1502, 323, 3493, 2632, 2585, 653, 2912, 1014, 1665, 2602, 3091, 1169, 1062, 94, 1053, 3295],
        "n_features": 41
    },
    "6": {
        "n_train": 48098,
        "n_features_in": 4443,
        "n_classes": 33,
        "filter_genes": false,
        "normalize": true,
        "log": true,
        "scale": true,
        "high_var": false,
        "ordered": true,
        "rho": 0.2857142857142857,
        "alpha": 0.0013504388926401081,
        "rs": 1000,
        "min_coverage": 6.088458311744034,
        "solution": [1665, 2205, 2491, 2534, 2765, 1421, 1388, 1794, 1871, 745, 2939, 3295, 1105, 3932, 923, 1224, 1384, 653, 283, 1054, 821, 2578, 1786, 1243, 58, 3260, 2276, 3411, 2335, 234, 912, 3192, 557, 1835, 3901, 2706, 1383, 2608, 1761, 4321, 1265, 2796, 1471, 4345, 2875, 1371],
        "n_features": 46
    },
    "7": {
        "n_train": 48098,
        "n_features_in": 4443,
        "n_classes": 33,
        "filter_genes": false,
        "normalize": true,
        "log": true,
        "scale": true,
        "high_var": false,
        "ordered": true,
        "rho": 0.2857142857142857,
        "alpha": 0.0015755120414134593,
        "rs": 1000,
        "min_coverage": 7.186665228684433,
        "solution": [1665, 2534, 2335, 748, 3558, 2205, 11, 1054, 3411, 2243, 1120, 1880, 2491, 4260, 1597, 3031, 1712, 2765, 653, 966, 1224, 86, 225, 745, 1871, 115, 157, 3260, 2659, 2944, 3318, 2532, 2246, 1418, 3091, 3642, 288, 3440, 1489, 652, 1053, 2774, 3295, 3669, 943, 62, 2479, 1367, 1265, 103, 233, 1044, 974],
        "n_features": 53
    },
    "8": {
        "n_train": 48098,
        "n_features_in": 4443,
        "n_classes": 33,
        "filter_genes": false,
        "normalize": true,
        "log": true,
        "scale": true,
        "high_var": false,
        "ordered": true,
        "rho": 0.2857142857142857,
        "alpha": 0.0018005851901868107,
        "rs": 1000,
        "min_coverage": 8.064866684377193,
        "solution": [115, 1665, 1388, 3454, 1417, 1421, 2534, 2206, 1054, 1880, 4336, 1120, 2586, 2006, 2491, 1835, 3066, 1871, 3447, 1652, 2578, 2893, 2546, 3932, 3453, 748, 225, 3915, 2055, 195, 3279, 1948, 1053, 1384, 867, 1171, 2276, 2362, 3318, 1105, 3061, 3214, 2073, 3244, 589, 1413, 1470, 4289, 2639, 652, 2706, 3260, 3112, 1912, 3877, 508, 2046, 2528, 1014, 747, 1044, 116],
        "n_features": 62
    },
    "9": {
        "n_train": 48098,
        "n_features_in": 4443,
        "n_classes": 33,
        "filter_genes": false,
        "normalize": true,
        "log": true,
        "scale": true,
        "high_var": false,
        "ordered": true,
        "rho": 0.25,
        "alpha": 0.002025658338960162,
        "rs": 1000,
        "min_coverage": 9.148353298427537,
        "solution": [1665, 2205, 3786, 2335, 1291, 1489, 3075, 1388, 2636, 241, 1437, 81, 2827, 748, 2534, 3311, 3411, 1597, 185, 2055, 449, 920, 2608, 2944, 2765, 2287, 1417, 1421, 1825, 727, 1384, 2586, 361, 528, 172, 2392, 2065, 1139, 3700, 2578, 1265, 1359, 1676, 3112, 2646, 417, 1383, 11, 919, 2423, 2484, 86, 2914, 1712, 1169, 50, 3260, 3061, 2532, 2577, 2682, 1928, 164, 1243, 2564, 3184],
        "n_features": 66
    },
    "10": {
        "n_train": 48098,
        "n_features_in": 4443,
        "n_classes": 33,
        "filter_genes": false,
        "normalize": true,
        "log": true,
        "scale": true,
        "high_var": false,
        "ordered": true,
        "rho": 0.25,
        "alpha": 0.0022507314877335135,
        "rs": 1000,
        "min_coverage": 10.001971801742911,
        "solution": [2206, 2205, 2546, 1139, 3932, 1679, 1243, 451, 2243, 115, 1489, 1880, 1816, 2003, 4260, 1597, 2055, 2505, 2765, 1054, 2276, 943, 2905, 1459, 1388, 1437, 1024, 2140, 1421, 2231, 1258, 2535, 821, 745, 2578, 1948, 86, 351, 2534, 1712, 2073, 2806, 844, 1384, 185, 3447, 1825, 3411, 4388, 1920, 358, 1985, 3260, 11, 436, 1062, 815, 4354, 3227, 2532, 557, 4321, 977, 1418, 1105, 1835, 653, 1417, 3184, 2471, 3777, 1614, 2537, 1000],
        "n_features": 74
    },
    "11": {
        "n_train": 48098,
        "n_features_in": 4443,
        "n_classes": 33,
        "filter_genes": false,
        "normalize": true,
        "log": true,
        "scale": true,
        "high_var": false,
        "ordered": true,
        "rho": 0.25,
        "alpha": 0.002475804636506865,
        "rs": 1000,
        "min_coverage": 11.005389505065978,
        "solution": [1665, 2006, 2206, 966, 1920, 1489, 3411, 2232, 86, 1243, 821, 1421, 3435, 912, 389, 2335, 1597, 1120, 3454, 115, 2003, 2534, 2608, 943, 834, 1367, 1679, 2243, 2471, 1880, 920, 1384, 1054, 3778, 919, 2586, 1655, 67, 2535, 923, 3585, 451, 185, 1240, 4321, 4345, 3066, 81, 1835, 1383, 2546, 157, 2578, 662, 417, 8, 94, 116, 1871, 2681, 1412, 2912, 230, 1608, 557, 351, 2843, 1786, 653, 109, 611, 1132, 863, 3611, 288, 1062, 3642, 1928, 2920, 172, 596],
        "n_features": 81
    },
    "12": {
        "n_train": 48098,
        "n_features_in": 4443,
        "n_classes": 33,
        "filter_genes": false,
        "normalize": true,
        "log": true,
        "scale": true,
        "high_var": false,
        "ordered": true,
        "rho": 0.2222222222222222,
        "alpha": 0.0027008777852802163,
        "rs": 1000,
        "min_coverage": 12.013890533242375,
        "solution": [2206, 1489, 2205, 3786, 4260, 1383, 1224, 1266, 3061, 1679, 86, 745, 1291, 1139, 2491, 2140, 1120, 11, 115, 2055, 2335, 2920, 3075, 1597, 3021, 3039, 1240, 2065, 358, 1871, 3806, 1388, 185, 1948, 973, 1421, 1297, 701, 834, 451, 3066, 1146, 1985, 50, 2003, 943, 761, 1243, 2232, 1054, 1676, 1920, 3237, 1234, 3244, 225, 4321, 3121, 234, 1105, 4354, 157, 2534, 3447, 2577, 1000, 3430, 3585, 1100, 1171, 249, 2362, 508, 634, 3901, 351, 2528, 2765, 2774, 1169, 3831, 2944, 155, 3112, 3866],
        "n_features": 85
    },
    "13": {
        "n_train": 48098,
        "n_features_in": 4443,
        "n_classes": 33,
        "filter_genes": false,
        "normalize": true,
        "log": true,
        "scale": true,
        "high_var": false,
        "ordered": true,
        "rho": 0.2222222222222222,
        "alpha": 0.002925950934053567,
        "rs": 1000,
        "min_coverage": 12.997862432384863,
        "solution": [378, 1665, 834, 351, 2206, 1388, 2491, 1120, 2205, 2243, 2534, 115, 2479, 745, 1384, 1417, 748, 2586, 589, 449, 3075, 1299, 3260, 2276, 3877, 2006, 1920, 1234, 1794, 1880, 1786, 1471, 2055, 1597, 1638, 1871, 4176, 2771, 765, 1679, 557, 3411, 1240, 528, 1722, 3901, 3031, 2765, 1383, 634, 81, 2806, 977, 1378, 3227, 663, 2665, 1054, 2608, 2920, 157, 1924, 4284, 1985, 2546, 1489, 827, 819, 2492, 62, 1418, 1797, 1171, 844, 3932, 567, 2578, 3502, 58, 219, 2499, 1835, 2602, 3715, 669, 926, 2057, 11, 1000],
        "n_features": 89
    },
    "14": {
        "n_train": 48098,
        "n_features_in": 4443,
        "n_classes": 33,
        "filter_genes": false,
        "normalize": true,
        "log": true,
        "scale": true,
        "high_var": false,
        "ordered": true,
        "rho": 0.2222222222222222,
        "alpha": 0.0031510240828269186,
        "rs": 1000,
        "min_coverage": 14.0119956638664,
        "solution": [1665, 2206, 2205, 1291, 2574, 1139, 115, 1597, 748, 923, 3066, 1786, 1679, 3411, 3558, 1373, 1054, 2231, 1243, 1871, 2939, 1388, 1722, 2491, 3112, 2003, 1100, 2335, 1417, 11, 2586, 86, 2246, 1967, 2484, 3295, 1120, 2190, 1471, 2243, 4014, 3831, 1707, 2912, 378, 4284, 4260, 1383, 3184, 3454, 1224, 505, 2928, 4321, 2493, 2944, 1608, 2562, 1676, 2534, 2711, 451, 157, 2392, 2318, 2055, 3502, 281, 2774, 2052, 1924, 1712, 2706, 2564, 2232, 3738, 1044, 351, 3041, 1377, 172, 4268, 920, 2499, 2765, 567, 779, 653, 1169, 2181, 1014, 1798, 3932, 1985, 2546, 3284, 2572, 225],
        "n_features": 98
    },
    "15": {
        "n_train": 48098,
        "n_features_in": 4443,
        "n_classes": 33,
        "filter_genes": false,
        "normalize": true,
        "log": true,
        "scale": true,
        "high_var": false,
        "ordered": true,
        "rho": 0.2,
        "alpha": 0.00337609723160027,
        "rs": 1000,
        "min_coverage": 15.089261521585286,
        "solution": [115, 1665, 2205, 1388, 2471, 2491, 3438, 1652, 378, 1384, 2534, 2765, 2238, 2206, 3295, 2287, 1825, 3061, 4005, 2243, 1471, 1417, 653, 1105, 1054, 3541, 3454, 86, 3126, 2771, 2370, 2659, 3066, 2944, 912, 648, 1545, 2586, 634, 1240, 589, 2055, 1791, 2774, 1120, 1546, 2939, 528, 3184, 1044, 1421, 3558, 2065, 4284, 3932, 1243, 1224, 43, 2706, 863, 4109, 3411, 3901, 351, 105, 1948, 358, 1489, 1724, 821, 4354, 389, 3585, 921, 3553, 247, 3727, 3447, 2578, 3121, 1014, 1470, 2854, 2564, 2232, 363, 1370, 1291, 3502, 1379, 3806, 1985, 3155, 169, 2086, 1695, 487, 694, 2029, 898, 1551, 3650, 611, 107, 11, 745, 3227, 1798, 917],
        "n_features": 109
    },
    "16": {
        "n_train": 48098,
        "n_features_in": 4443,
        "n_classes": 33,
        "filter_genes": false,
        "normalize": true,
        "log": true,
        "scale": true,
        "high_var": false,
        "ordered": true,
        "rho": 0.2,
        "alpha": 0.0036011703803736214,
        "rs": 1000,
        "min_coverage": 16.003970429301262,
        "solution": [2206, 115, 1665, 2205, 4260, 2335, 1240, 3438, 1291, 378, 1489, 1388, 1139, 1652, 2231, 2055, 1383, 3075, 748, 1920, 1546, 634, 2491, 1545, 1712, 3295, 86, 62, 498, 2564, 2546, 508, 1880, 2586, 1798, 2774, 2920, 1882, 1791, 3642, 1985, 2088, 3411, 1384, 1679, 2392, 241, 2238, 1417, 1825, 2108, 1871, 449, 3260, 361, 3442, 3155, 2572, 950, 3066, 2574, 1986, 3031, 1224, 414, 103, 1370, 2471, 2970, 351, 1638, 3502, 567, 1000, 74, 247, 1146, 844, 3454, 912, 234, 1762, 461, 2528, 2639, 3121, 2578, 2928, 1835, 2006, 3831, 3090, 2608, 563, 1054, 230, 1297, 2939, 2109, 3063, 1243, 3901, 1265, 2912, 3877, 3213, 908, 509, 3756, 4338, 2029, 973, 2115, 11],
        "n_features": 114
    },
    "17": {
        "n_train": 48098,
        "n_features_in": 4443,
        "n_classes": 33,
        "filter_genes": false,
        "normalize": true,
        "log": true,
        "scale": true,
        "high_var": false,
        "ordered": true,
        "rho": 0.2,
        "alpha": 0.0038262435291469728,
        "rs": 1000,
        "min_coverage": 17.057342495769262,
        "solution": [1388, 1665, 2206, 2205, 1384, 1105, 2243, 821, 1224, 1835, 653, 2847, 779, 2534, 1471, 115, 2546, 1920, 1421, 2335, 234, 2527, 3901, 137, 1373, 2238, 1297, 50, 2003, 1597, 745, 497, 2491, 3066, 1140, 3877, 1120, 563, 3075, 3295, 919, 1780, 2659, 363, 920, 3454, 3031, 3558, 3932, 449, 748, 2586, 1291, 2493, 846, 2029, 1437, 3727, 1712, 101, 1000, 844, 378, 1370, 596, 351, 2920, 2055, 912, 2570, 765, 3447, 2392, 3812, 1482, 3260, 1985, 2771, 2998, 2471, 3041, 1489, 2639, 146, 2939, 3112, 1258, 1418, 1655, 3192, 4284, 1827, 3411, 81, 2682, 834, 2479, 2052, 1383, 1948, 977, 451, 3985, 2578, 242, 509, 164, 1139, 2912, 2827, 557, 11, 882, 1444, 973, 567, 350, 3089, 657, 2605, 1044],
        "n_features": 121
    },
    "18": {
        "n_train": 48098,
        "n_features_in": 4443,
        "n_classes": 33,
        "filter_genes": false,
        "normalize": true,
        "log": true,
        "scale": true,
        "high_var": false,
        "ordered": true,
        "rho": 0.18181818181818182,
        "alpha": 0.004051316677920324,
        "rs": 1000,
        "min_coverage": 18.04290776513517,
        "solution": [2206, 1665, 2205, 1384, 115, 4260, 1489, 1113, 748, 1299, 3411, 1471, 1388, 2140, 378, 653, 2335, 2944, 2441, 1105, 1597, 1679, 920, 1240, 1835, 3553, 1331, 11, 3295, 2636, 2877, 834, 3031, 2570, 1762, 4284, 2659, 2546, 86, 247, 2231, 844, 2665, 1146, 3932, 2243, 745, 701, 567, 2586, 2572, 1383, 2532, 2534, 1088, 1871, 417, 1202, 1139, 2232, 1374, 1546, 2914, 821, 2003, 3786, 281, 1297, 1224, 943, 1695, 1120, 2771, 1437, 1265, 2423, 4005, 351, 2491, 1737, 3642, 1243, 3985, 1417, 43, 1132, 926, 1761, 1827, 589, 1587, 2652, 2318, 2238, 3072, 1724, 1791, 233, 2057, 1379, 2181, 2528, 590, 172, 1054, 1291, 2765, 557, 3404, 2539, 973, 2217, 3227, 2806, 1603, 1062, 2807, 116, 960, 1413, 2577, 3061, 1329, 4129, 2706, 1344],
        "n_features": 126
    },
    "19": {
        "n_train": 48098,
        "n_features_in": 4443,
        "n_classes": 33,
        "filter_genes": false,
        "normalize": true,
        "log": true,
        "scale": true,
        "high_var": false,
        "ordered": true,
        "rho": 0.18181818181818182,
        "alpha": 0.0042763898266936756,
        "rs": 1000,
        "min_coverage": 19.082629248092417,
        "solution": [2206, 1665, 2205, 1139, 1384, 1597, 1388, 2564, 2006, 1140, 1054, 115, 378, 1489, 1105, 2276, 1679, 1471, 2491, 1291, 1299, 1652, 2335, 3411, 592, 1346, 2140, 3075, 745, 2636, 2546, 2534, 2939, 1546, 3295, 1383, 86, 567, 1017, 557, 1871, 1603, 2944, 4260, 1120, 3016, 451, 3244, 921, 2370, 355, 2807, 1417, 1437, 1966, 4259, 4341, 3440, 2586, 3451, 920, 1114, 3031, 1880, 844, 2578, 3901, 1158, 1827, 1438, 2052, 81, 281, 1786, 834, 2238, 1243, 2532, 2055, 1248, 2029, 351, 1297, 318, 653, 1608, 2540, 1373, 233, 2243, 116, 2125, 2008, 2682, 634, 1014, 1418, 2659, 2425, 964, 1948, 2003, 1311, 2539, 4321, 2555, 1470, 521, 943, 508, 1224, 249, 2912, 242, 900, 2639, 3307, 608, 3063, 4176, 1370, 3843, 3184, 3121, 4186, 2535, 1761, 1411, 43, 1727, 1044, 2137, 294, 652, 525, 709, 1062],
        "n_features": 137
    },
    "20": {
        "n_train": 48098,
        "n_features_in": 4443,
        "n_classes": 33,
        "filter_genes": false,
        "normalize": true,
        "log": true,
        "scale": true,
        "high_var": false,
        "ordered": true,
        "rho": 0.18181818181818182,
        "alpha": 0.004501462975467027,
        "rs": 1000,
        "min_coverage": 20.006557776825503,
        "solution": [378, 1665, 2206, 2205, 1105, 2243, 1489, 1120, 4284, 1383, 1139, 1240, 1291, 2190, 4260, 1373, 1388, 1014, 2648, 1421, 3295, 923, 115, 1679, 2491, 2875, 2055, 351, 1920, 389, 1054, 116, 748, 1417, 497, 1597, 1299, 2765, 701, 2335, 745, 81, 634, 1985, 241, 1825, 2939, 1502, 2528, 834, 3727, 361, 3227, 2928, 195, 2534, 1791, 3078, 821, 1000, 1265, 3411, 920, 1155, 2392, 3447, 2682, 653, 3502, 2578, 172, 973, 62, 3986, 1248, 1587, 37, 2086, 3454, 1880, 2532, 2546, 451, 8, 294, 3184, 234, 1871, 3585, 2564, 1986, 1707, 1695, 86, 648, 3866, 2469, 2605, 2608, 626, 1722, 3169, 1948, 1727, 2807, 3877, 2639, 3932, 3395, 2806, 2217, 508, 97, 2706, 3061, 2659, 1882, 1243, 1835, 2065, 43, 815, 1411, 2920, 1827, 155, 4050, 4345, 1786, 1367, 2577, 563, 557, 1470, 1044, 3033, 832, 58, 2539, 732, 185, 1088, 1651, 4118],
        "n_features": 144
    },
    "21": {
        "n_train": 48098,
        "n_features_in": 4443,
        "n_classes": 33,
        "filter_genes": false,
        "normalize": true,
        "log": true,
        "scale": true,
        "high_var": false,
        "ordered": true,
        "rho": 0.16666666666666666,
        "alpha": 0.004726536124240378,
        "rs": 1000,
        "min_coverage": 21.033000356517732,
        "solution": [1665, 2206, 115, 2205, 1291, 748, 2335, 1240, 920, 2491, 4284, 1384, 1835, 1105, 2875, 2243, 2586, 1383, 1054, 265, 2639, 3295, 3727, 2893, 2636, 1597, 1545, 3438, 1388, 1638, 1489, 1139, 4260, 1679, 497, 86, 1652, 2944, 378, 648, 1417, 2108, 3031, 2276, 2577, 1825, 1140, 3502, 3183, 1437, 1000, 2825, 3284, 3786, 417, 634, 1459, 3126, 2198, 1014, 195, 2665, 3901, 2912, 919, 1221, 2827, 3075, 449, 1265, 94, 2527, 3192, 3411, 3244, 3112, 2535, 834, 1592, 2920, 1762, 3066, 663, 2546, 596, 1791, 1880, 2566, 2562, 2572, 2980, 72, 3577, 3585, 1698, 779, 4229, 351, 2534, 1695, 157, 2807, 241, 1053, 2564, 2528, 1863, 4050, 2578, 3866, 557, 2605, 960, 1100, 2181, 567, 3078, 819, 1316, 528, 589, 2006, 912, 1920, 361, 926, 973, 397, 1288, 1085, 1191, 1224, 1158, 2008, 410, 2086, 2681, 1234, 1352, 2422, 1871, 355, 53, 3313, 1044, 1062, 1948, 1243, 3061, 747, 334, 1370],
        "n_features": 152
    },
    "22": {
        "n_train": 48098,
        "n_features_in": 4443,
        "n_classes": 33,
        "filter_genes": false,
        "normalize": true,
        "log": true,
        "scale": true,
        "high_var": false,
        "ordered": true,
        "rho": 0.16666666666666666,
        "alpha": 0.00495160927301373,
        "rs": 1000,
        "min_coverage": 22.06110522407107,
        "solution": [834, 1665, 2205, 378, 1384, 115, 2206, 2659, 2527, 1597, 923, 3440, 1835, 2534, 1139, 3438, 116, 2335, 3078, 2875, 1240, 317, 748, 334, 745, 1155, 1388, 2893, 1471, 1202, 2108, 1243, 1417, 451, 3750, 608, 72, 2586, 2636, 1587, 1786, 2765, 1432, 2055, 3404, 3155, 2608, 3066, 2682, 2003, 2546, 1224, 819, 3295, 1986, 1651, 596, 389, 294, 808, 498, 449, 2564, 1880, 4011, 844, 3447, 1105, 3502, 1054, 2665, 4324, 1370, 4284, 497, 2774, 2198, 3411, 2491, 1062, 2232, 1555, 756, 2246, 1676, 966, 3126, 2264, 1000, 4260, 842, 163, 2771, 1088, 563, 2276, 3039, 1791, 2920, 3715, 1737, 3877, 351, 1352, 2681, 62, 2492, 172, 3061, 318, 2806, 1024, 2008, 1265, 2086, 2711, 1889, 8, 2160, 1053, 3121, 3257, 234, 1014, 103, 943, 110, 1695, 1378, 2471, 931, 1371, 3677, 920, 2827, 281, 4151, 964, 3260, 1762, 11, 3885, 653, 2450, 2721, 1827, 1100, 1761, 233, 1390, 2939, 508, 4321, 3843, 1585, 2115, 1470, 81, 137, 1158, 747, 2231],
        "n_features": 162
    },
    "23": {
        "n_train": 48098,
        "n_features_in": 4443,
        "n_classes": 33,
        "filter_genes": false,
        "normalize": true,
        "log": true,
        "scale": true,
        "high_var": false,
        "ordered": true,
        "rho": 0.16666666666666666,
        "alpha": 0.005176682421787081,
        "rs": 1000,
        "min_coverage": 23.03533711610362,
        "solution": [115, 2205, 2206, 1665, 1384, 1383, 2006, 1762, 1105, 1299, 2564, 2335, 1920, 4321, 1597, 1224, 1139, 2534, 1388, 2527, 2491, 451, 1679, 2243, 748, 86, 378, 3318, 1489, 1120, 966, 1243, 172, 62, 2231, 528, 634, 81, 2875, 3075, 2636, 653, 1291, 11, 2659, 3411, 923, 1561, 1835, 2055, 417, 1014, 3831, 2806, 3885, 1871, 4284, 2771, 1297, 814, 2572, 1695, 2546, 3438, 480, 497, 1346, 4324, 3454, 2765, 355, 2003, 745, 1794, 2827, 912, 2586, 920, 2276, 701, 2535, 4005, 3061, 1265, 926, 1240, 1985, 834, 4118, 3260, 361, 1418, 2294, 2450, 2392, 2578, 351, 1417, 1882, 1054, 3447, 3541, 449, 765, 3901, 589, 1370, 1825, 363, 2608, 1248, 376, 1408, 3553, 4354, 3066, 2540, 3072, 3531, 3932, 1437, 242, 234, 2029, 563, 2238, 657, 2605, 155, 3866, 863, 2968, 3727, 3184, 1761, 358, 265, 340, 900, 3311, 1493, 410, 2181, 1623, 1585, 3877, 2681, 508, 821, 2469, 1877, 241, 1204, 2528, 2970, 732, 2422, 2008, 1827, 336, 4250, 2602, 652, 827, 219, 2423, 2577],
        "n_features": 167
    },
    "24": {
        "n_train": 48098,
        "n_features_in": 4443,
        "n_classes": 33,
        "filter_genes": false,
        "normalize": true,
        "log": true,
        "scale": true,
        "high_var": false,
        "ordered": true,
        "rho": 0.15384615384615385,
        "alpha": 0.0054017555705604325,
        "rs": 1000,
        "min_coverage": 24.00118706462672,
        "solution": [1665, 115, 2205, 3055, 556, 1105, 1216, 2206, 378, 1054, 2491, 2528, 834, 4260, 2527, 1291, 1243, 1920, 1388, 4341, 2586, 3585, 265, 3986, 1651, 634, 2238, 1489, 3411, 1224, 505, 919, 1384, 1014, 3075, 674, 2765, 3438, 3126, 4321, 1417, 2534, 1160, 155, 920, 2243, 3786, 1139, 3727, 2232, 137, 2264, 745, 449, 1597, 2055, 3295, 1794, 101, 748, 3404, 86, 1835, 1471, 1240, 1737, 844, 2335, 172, 557, 1791, 2006, 2471, 498, 1925, 1786, 2546, 1880, 1383, 3066, 417, 50, 1762, 1695, 1088, 608, 1265, 2479, 2806, 461, 3294, 2318, 3031, 3502, 2807, 2928, 361, 110, 2771, 3439, 1604, 567, 234, 1470, 2665, 3844, 2190, 3447, 1385, 2540, 497, 451, 898, 606, 2029, 2827, 389, 1371, 3436, 414, 1986, 116, 3021, 3200, 1724, 653, 1493, 1346, 2572, 4354, 814, 508, 1062, 929, 1948, 765, 2564, 2362, 11, 4259, 58, 563, 581, 589, 2561, 43, 3052, 1712, 2774, 3169, 2086, 2539, 1248, 480, 838, 3386, 1288, 2878, 294, 3815, 1370, 2912, 3184, 3738, 3831, 1169, 2577, 964, 1266, 1044, 3121, 1940, 2125, 2236, 1697, 1100, 1158],
        "n_features": 177
    },
    "25": {
        "n_train": 48098,
        "n_features_in": 4443,
        "n_classes": 33,
        "filter_genes": false,
        "normalize": true,
        "log": true,
        "scale": true,
        "high_var": false,
        "ordered": true,
        "rho": 0.15384615384615385,
        "alpha": 0.005626828719333784,
        "rs": 1000,
        "min_coverage": 25.005548004992306,
        "solution": [2206, 115, 2205, 378, 1665, 1384, 172, 1388, 2574, 4284, 1291, 834, 4229, 2491, 3064, 1105, 920, 1471, 748, 2006, 1920, 567, 2534, 2264, 634, 1652, 2527, 2335, 919, 3231, 1882, 340, 842, 1240, 1597, 449, 653, 745, 964, 361, 4011, 451, 1139, 2243, 86, 1432, 1880, 2392, 1120, 966, 2160, 2086, 2505, 3932, 233, 1224, 185, 2783, 2232, 3493, 1489, 2586, 557, 2659, 1835, 2043, 3585, 1370, 11, 1948, 589, 3126, 1383, 1044, 1620, 1871, 414, 1786, 3404, 81, 3031, 2003, 103, 2528, 620, 1014, 1000, 3985, 2025, 1421, 814, 821, 2337, 2665, 1470, 2318, 351, 943, 137, 1437, 2246, 2564, 1373, 3295, 3715, 1724, 3502, 2771, 4345, 2827, 2632, 2008, 1722, 2765, 2546, 648, 3901, 657, 325, 3677, 608, 3318, 1712, 417, 3121, 2875, 2550, 929, 1608, 1698, 2854, 2539, 1459, 62, 1587, 509, 912, 973, 4419, 2807, 2422, 611, 1258, 389, 3877, 2806, 2981, 2432, 3066, 926, 1695, 2575, 97, 2181, 265, 1379, 1311, 3091, 563, 4341, 3831, 2236, 1296, 2602, 2686, 1797, 1655, 2572, 1169, 642, 238, 370, 1418, 1344, 234, 819, 240, 294, 3760, 2038, 694, 4324, 116, 3257, 759, 3183, 3642],
        "n_features": 187
    }
}